LICENSE
MANIFEST.in
README.md
setup.cfg
setup.py
src/canto/__init__.py
src/canto/admin.py
src/canto/apps.py
src/canto/client.py
src/canto/forms.py
src/canto/models.py
src/canto/services.py
src/canto/urls.py
src/canto/views.py
src/canto/widgets.py
src/canto/management/commands/canto_refresh_token.py
src/canto/migrations/0001_initial.py
src/canto/migrations/__init__.py
src/canto/static/js/canto/canto.js
src/canto/static/styles/canto/canto.css
src/canto/templates/canto/library.html
src/canto/templates/canto/settings.html
src/canto/tests/__init__.py
src/canto/tests/tests.py
src/canto/tests/urls.py
src/django_canto.egg-info/PKG-INFO
src/django_canto.egg-info/SOURCES.txt
src/django_canto.egg-info/dependency_links.txt
src/django_canto.egg-info/requires.txt
src/django_canto.egg-info/top_level.txt